tkapp/__init__.py
tkapp/tkapp.py
tkapp-0.0.1.dist-info/LICENSE
tkapp-0.0.1.dist-info/METADATA
tkapp-0.0.1.dist-info/WHEEL
tkapp-0.0.1.dist-info/top_level.txt
tkapp-0.0.1.dist-info/RECORD
